linkmedic-0.9.0.dist-info/METADATA
linkmedic-0.9.0.dist-info/WHEEL
linkmedic-0.9.0.dist-info/entry_points.txt
linkmedic-0.9.0.dist-info/licenses/LICENSE
linkmedic/__init__.py
linkmedic/__main__.py
linkmedic/diagnose.py
linkmedic/logbook.py
linkmedic/reception.py
linkmedic/webmaster.py
linkmedic/webserver.py
linkmedic-0.9.0.dist-info/RECORD
