Metadata-Version: 2.1
Name: linkmedic
Version: 0.9.0
Summary: Website links checker
Keywords: html,odf,xml
Author: M. Farzalipour Tabriz
License: BSD-3-Clause
Classifier: Development Status :: 3 - Alpha
Classifier: Environment :: Console
Classifier: Intended Audience :: Developers
Classifier: Programming Language :: Python :: 3
Classifier: Topic :: Internet :: WWW/HTTP :: Site Management :: Link Checking
Project-URL: source, https://gitlab.mpcdf.mpg.de/tbz/linkmedic.git
Project-URL: documentation, https://tbz.pages.mpcdf.de/linkmedic/
Requires-Python: >=3.9
Requires-Dist: beautifulsoup4>=4.13.0
Requires-Dist: coloredlogs>=15.0.0
Requires-Dist: lxml>=5.4.0
Requires-Dist: requests>=2.32.0
